livekit/plugins/dataspike/__init__.py
livekit/plugins/dataspike/detector.py
livekit/plugins/dataspike/log.py
livekit/plugins/dataspike/py.typed
livekit/plugins/dataspike/schema_pb2.py
livekit/plugins/dataspike/version.py
dataspike_livekit_plugins-1.2.17.dist-info/METADATA
dataspike_livekit_plugins-1.2.17.dist-info/WHEEL
dataspike_livekit_plugins-1.2.17.dist-info/RECORD
