Metadata-Version: 2.4
Name: dataspike-livekit-plugins
Version: 1.2.17
Summary: Dataspike deepfake detection plugin for LiveKit Agents
Project-URL: Documentation, https://docs.dataspike.io
Project-URL: Website, https://dataspike.io/
Project-URL: Source, https://github.com/dataspike-io/agents
Author-email: LiveKit <hello@livekit.io>
License-Expression: Apache-2.0
Keywords: dataspike,livekit,realtime,video,webrtc
Classifier: Intended Audience :: Developers
Classifier: Programming Language :: Python :: 3
Classifier: Programming Language :: Python :: 3 :: Only
Classifier: Programming Language :: Python :: 3.11
Classifier: Programming Language :: Python :: 3.12
Classifier: Topic :: Multimedia :: Video
Classifier: Topic :: Scientific/Engineering :: Artificial Intelligence
Requires-Python: >=3.9.0
Requires-Dist: betterproto==2.0.0b6
Requires-Dist: livekit-agents>=1.2.15
Requires-Dist: protobuf>=3.20.0
